itempicture/__init__.py
itempicture/cli.py
itempicture/processor.py
itempicture/svg.py
itempicture/utils.py
itempicture-1.0.0.dist-info/LICENSE
itempicture-1.0.0.dist-info/METADATA
itempicture-1.0.0.dist-info/WHEEL
itempicture-1.0.0.dist-info/entry_points.txt
itempicture-1.0.0.dist-info/top_level.txt
itempicture-1.0.0.dist-info/RECORD
