Metadata-Version: 2.1
Name: itempicture
Version: 1.0.0
Summary: Application for generate images in same style with titles
Home-page: https://github.com/machineandme/itempicture
Author: Machine & Me
Author-email: ceo@machineand.me
License: UNKNOWN
Project-URL: Bug Reports, https://github.com/machineandme/itempicture/issues
Project-URL: Funding, https://www.patreon.com/machineandme
Project-URL: Source, https://github.com/machineandme/itempicture
Keywords: generate design images with same style and custom name
Platform: UNKNOWN
Classifier: Development Status :: 4 - Beta
Classifier: Intended Audience :: Developers
Classifier: Topic :: Software Development :: User Interfaces
Classifier: License :: OSI Approved :: MIT License
Classifier: Programming Language :: Python :: 3
Requires-Python: >=3.5.*
Requires-Dist: cairocffi (==1.1.0)
Requires-Dist: cairosvg (==2.4.2)
Requires-Dist: cffi (==1.12.3)
Requires-Dist: cssselect2 (==0.2.2)
Requires-Dist: defusedxml (==0.6.0)
Requires-Dist: fire (==0.2.1)
Requires-Dist: pillow (==6.1.0)
Requires-Dist: pycparser (==2.19)
Requires-Dist: six (==1.12.0)
Requires-Dist: termcolor (==1.1.0)
Requires-Dist: tinycss2 (==1.0.2)
Requires-Dist: webencodings (==0.5.1)
